AUTHORS
CODE_OF_CONDUCT.md
CONTRIBUTING.md
LICENSE
README.md
requirements.txt
requirements_base.txt
requirements_extra_pip.txt
setup.cfg
setup.py
avni/__init__.py
avni/constants.py
avni/gui.py
avni/version.py
avni.egg-info/PKG-INFO
avni.egg-info/SOURCES.txt
avni.egg-info/dependency_links.txt
avni.egg-info/requires.txt
avni.egg-info/top_level.txt
avni/api/__init__.py
avni/api/applet_support.py
avni/api/client.py
avni/api/cmt.py
avni/api/f2py.py
avni/api/model.py
avni/api/traveltimes.py
avni/config/attributes.ini
avni/config/f2py.ini
avni/config/planets.ini
avni/config/units.ini
avni/data/CMT.py
avni/data/NM.py
avni/data/SW.py
avni/data/TT.py
avni/data/__init__.py
avni/data/common.py
avni/f2py/CAGCRAYS/bullen.f
avni/f2py/CAGCRAYS/cagcrays_pm.f
avni/f2py/CAGCRAYS/conv2geocen.f
avni/f2py/CAGCRAYS/drspledr.f
avni/f2py/CAGCRAYS/dxt.f
avni/f2py/CAGCRAYS/emcommon.h
avni/f2py/CAGCRAYS/emcommonb.h
avni/f2py/CAGCRAYS/evem.f
avni/f2py/CAGCRAYS/evemb.f
avni/f2py/CAGCRAYS/evemdr.f
avni/f2py/CAGCRAYS/evemell.f
avni/f2py/CAGCRAYS/fdrays.f
avni/f2py/CAGCRAYS/fqs.f
avni/f2py/CAGCRAYS/get_branch.f
avni/f2py/CAGCRAYS/get_ishflag.f
avni/f2py/CAGCRAYS/getptab.f
avni/f2py/CAGCRAYS/prange.f
avni/f2py/CAGCRAYS/psvrayin.f
avni/f2py/CAGCRAYS/qtau.f
avni/f2py/CAGCRAYS/qtauall.f
avni/f2py/CAGCRAYS/qtauzero.f
avni/f2py/CAGCRAYS/rays.h
avni/f2py/CAGCRAYS/rayseq.f
avni/f2py/CAGCRAYS/reademb.f
avni/f2py/CAGCRAYS/reademfl.f
avni/f2py/CAGCRAYS/readptab.f
avni/f2py/CAGCRAYS/tt_predict.f
avni/f2py/CAGCRAYS/wgint.f
avni/f2py/CAGCRAYS/wgray.f
avni/f2py/HYPOSRC/DiffTime.f
avni/f2py/HYPOSRC/getcmt5.f
avni/f2py/HYPOSRC/getcmtbyname.f
avni/f2py/HYPOSRC/loadnbn2memory.f
avni/f2py/HYPOSRC/nbninfo.h
avni/f2py/HYPOSRC/readnbn.f
avni/f2py/INV/drsple.f
avni/f2py/INV/drspln.f
avni/f2py/INV/vbspl.f
avni/f2py/LIBSRC/geolib/ddelaz.f
avni/f2py/LIBSRC/geolib/ddelazgc.f
avni/f2py/LIBSRC/geolib/delaz.f
avni/f2py/LIBSRC/geolib/delazgc.f
avni/f2py/LIBSRC/geolib/drspleder.f
avni/f2py/LIBSRC/geolib/julday.f
avni/f2py/LIBSRC/geolib/legndr.f
avni/f2py/LIBSRC/geolib/lpyr.f
avni/f2py/LIBSRC/geolib/monday.f
avni/f2py/LIBSRC/geolib/pdaz.f
