Metadata-Version: 2.1
Name: avni
Version: 0.1.0
Summary: Analysis and Visualization toolkit for plaNetary Inferences provides web-based and backend code access to tools, techniques, models and data.
Home-page: https://avni.globalseismology.org
Author: Pritwiraj Moulik
Author-email: moulik@caa.columbia.edu
License: GPL
Project-URL: Documentation, https://avni.globalseismology.org
Project-URL: Source, https://github.com/globalseismology/avni
Project-URL: Tracker, https://github.com/globalseismology/avni/issues
Keywords: earth-science,earth-observation,earthquake,earth,earthquake-data,geology,geophysics,geophysical-inversions,seismology,seismic-inversion,seismic-waves,seismic-tomography,mineral,geochemistry,geodesy,physics,modeling,modeling-tool,model,geodynamics
Platform: any
Classifier: License :: OSI Approved :: GNU General Public License v3 or later (GPLv3+)
Classifier: Programming Language :: Fortran
Classifier: Programming Language :: Python :: 3
Classifier: Intended Audience :: Science/Research
Classifier: Topic :: Education
Classifier: Natural Language :: English
Requires-Python: >=3.7
Provides-Extra: all
License-File: LICENSE
License-File: AUTHORS
